deductable/__init__.py
deductable/core.py
example/main.py
deductable-2025.10.1.dist-info/METADATA
deductable-2025.10.1.dist-info/WHEEL
deductable-2025.10.1.dist-info/top_level.txt
deductable-2025.10.1.dist-info/RECORD
