Metadata-Version: 2.4
Name: deductable
Version: 2025.10.1
Summary: A Python library for defining and applying column functions to DuckDB tables
Author-email: djoek <github@djoek.net>
License: MIT
Project-URL: Homepage, https://github.com/djoek/deductable
Project-URL: Bug Tracker, https://github.com/djoek/deductable/issues
Classifier: Development Status :: 3 - Alpha
Classifier: Intended Audience :: Developers
Classifier: License :: OSI Approved :: MIT License
Classifier: Programming Language :: Python :: 3
Classifier: Programming Language :: Python :: 3.13
Classifier: Topic :: Database
Classifier: Topic :: Software Development :: Libraries :: Python Modules
Requires-Python: >=3.13
Requires-Dist: duckdb>=1.4.1
Requires-Dist: loguru>=0.7.3
Requires-Dist: pandas>=2.3.3
